daboi/__init__.py
daboi/instabot.py
daboi-0.1.3.dist-info/METADATA
daboi-0.1.3.dist-info/WHEEL
daboi-0.1.3.dist-info/top_level.txt
daboi-0.1.3.dist-info/RECORD
