Metadata-Version: 2.1
Name: daboi
Version: 0.1.3
Summary: Selenium instagram automation.
Home-page: https://github.com/msgent/daboi
Author: Marcel Szimonisz
Author-email: marcel.simik@gmail.com
License: UNKNOWN
Platform: UNKNOWN
Classifier: Programming Language :: Python :: 3
Classifier: License :: OSI Approved :: MIT License
Classifier: Operating System :: OS Independent
Classifier: Development Status :: 4 - Beta
Requires-Python: >=3.6
Requires-Dist: selenium (>=3.141.0)
